catpig/__init__.py
catpig/catpig.py
catpig-0.3.0.dist-info/LICENSE
catpig-0.3.0.dist-info/METADATA
catpig-0.3.0.dist-info/WHEEL
catpig-0.3.0.dist-info/top_level.txt
catpig-0.3.0.dist-info/RECORD
